CHANGELOG.md
LICENSE.txt
MANIFEST.in
README.md
development.pip
requirements.pip
setup.py
amico/__init__.py
amico/amico.py
amico.egg-info/PKG-INFO
amico.egg-info/SOURCES.txt
amico.egg-info/dependency_links.txt
amico.egg-info/requires.txt
amico.egg-info/top_level.txt