Metadata-Version: 1.1
Name: amico
Version: 1.0.1
Summary: Relationships (e.g. friendships) backed by Redis.
Home-page: https://github.com/agoragames/amico-python
Author: David Czarnecki
Author-email: dczarnecki@agoragames.com
License: LICENSE.txt
Keywords: python,redis,friendships
Platform: UNKNOWN
Classifier: Development Status :: 5 - Production/Stable
Classifier: License :: OSI Approved :: MIT License
Classifier: Intended Audience :: Developers
Classifier: Operating System :: POSIX
Classifier: Topic :: Communications
Classifier: Topic :: System :: Distributed Computing
Classifier: Topic :: Software Development :: Libraries :: Python Modules
Classifier: Programming Language :: Python
Classifier: Programming Language :: Python :: 2.7
Classifier: Programming Language :: Python :: 3
Classifier: Topic :: Software Development :: Libraries
